print_tricks/__init__.py
print_tricks/tricks.py
print_tricks-1.0.dist-info/LICENSE
print_tricks-1.0.dist-info/METADATA
print_tricks-1.0.dist-info/WHEEL
print_tricks-1.0.dist-info/top_level.txt
print_tricks-1.0.dist-info/RECORD
