Metadata-Version: 2.1
Name: print-tricks
Version: 1.0
Summary: Typewrite style printing and fly-in text in python3
Author-email: ANinjaDREW <andrewsharon@gmx.com>
Project-URL: Homepage, https://github.com/andyswings/print_tricks
Project-URL: Bug Tracker, https://github.com/andyswings/print_tricks/issues
Classifier: Programming Language :: Python :: 3
Classifier: License :: OSI Approved :: MIT License
Classifier: Operating System :: OS Independent
Requires-Python: >=3.7
License-File: LICENSE
